puzzlestream/__init__.py
puzzlestream/__main__.py
puzzlestream/launch.py
puzzlestream/apps/__init__.py
puzzlestream/apps/base.py
puzzlestream/apps/plot/__init__.py
puzzlestream/apps/plot/app.py
puzzlestream/backend/__init__.py
puzzlestream/backend/config.py
puzzlestream/backend/dict.py
puzzlestream/backend/figure.py
puzzlestream/backend/notificationsystem.py
puzzlestream/backend/numpymodel2D.py
puzzlestream/backend/print.py
puzzlestream/backend/progressupdate.py
puzzlestream/backend/reference.py
puzzlestream/backend/signal.py
puzzlestream/backend/standardtablemodel.py
puzzlestream/backend/status.py
puzzlestream/backend/stream.py
puzzlestream/backend/streamsection.py
puzzlestream/backend/test.py
puzzlestream/backend/tracebackmodel.py
puzzlestream/backend/treemodel.py
puzzlestream/backend/worker.py
puzzlestream/fonts/FiraCode-Regular.ttf
puzzlestream/fonts/Roboto-Black.ttf
puzzlestream/fonts/Roboto-BlackItalic.ttf
puzzlestream/fonts/Roboto-Bold.ttf
puzzlestream/fonts/Roboto-BoldItalic.ttf
puzzlestream/fonts/Roboto-Italic.ttf
puzzlestream/fonts/Roboto-Light.ttf
puzzlestream/fonts/Roboto-LightItalic.ttf
puzzlestream/fonts/Roboto-Medium.ttf
puzzlestream/fonts/Roboto-MediumItalic.ttf
puzzlestream/fonts/Roboto-Regular.ttf
puzzlestream/fonts/Roboto-Thin.ttf
puzzlestream/fonts/Roboto-ThinItalic.ttf
puzzlestream/icons/Jigsaw_Puzzle.svg
puzzlestream/icons/Logo.svg
puzzlestream/icons/Puzzlestream.ico
puzzlestream/icons/Puzzlestream.png
puzzlestream/icons/Puzzlestream_1024.png
puzzlestream/icons/Puzzlestream_128.png
puzzlestream/icons/Puzzlestream_256.png
puzzlestream/icons/Puzzlestream_32.png
puzzlestream/icons/Puzzlestream_512.png
puzzlestream/icons/Puzzlestream_64.png
puzzlestream/icons/back_blue.png
puzzlestream/icons/back_white.png
puzzlestream/icons/copy_blue_in.png
puzzlestream/icons/copy_blue_out.png
puzzlestream/icons/cut_blue_in.png
puzzlestream/icons/cut_blue_out.png
puzzlestream/icons/down-arrow-3.png
puzzlestream/icons/fetch.png
puzzlestream/icons/folder_blue.png
puzzlestream-0.9.5.dist-info/LICENSE.txt
puzzlestream-0.9.5.dist-info/METADATA
puzzlestream-0.9.5.dist-info/WHEEL
puzzlestream-0.9.5.dist-info/entry_points.txt
puzzlestream-0.9.5.dist-info/top_level.txt
puzzlestream-0.9.5.dist-info/RECORD
