Metadata-Version: 2.1
Name: puzzlestream
Version: 0.9.5
Summary: Data analysis software
Home-page: https://puzzlestream.org
Author: Nils Holle, Fabian Theissen
Author-email: info@puzzlestream.org
License: MIT
Keywords: data analysis
Platform: UNKNOWN
Classifier: Development Status :: 3 - Alpha
Classifier: Intended Audience :: Developers
Classifier: Topic :: Software Development :: Build Tools
Classifier: License :: OSI Approved :: MIT License
Classifier: Programming Language :: Python :: 3
Classifier: Programming Language :: Python :: 3.5
Classifier: Programming Language :: Python :: 3.6
Classifier: Programming Language :: Python :: 3.7
Classifier: Programming Language :: Python :: 3.8
Requires-Dist: numpy
Requires-Dist: scipy
Requires-Dist: matplotlib
Requires-Dist: pandas
Requires-Dist: PyQt5
Requires-Dist: pyqtgraph
Requires-Dist: appdirs
Requires-Dist: tabulate
Requires-Dist: psutil
Requires-Dist: diskcache
Requires-Dist: gitpython
Requires-Dist: jedi
Requires-Dist: pyqode.python
Requires-Dist: bs4
Requires-Dist: lxml
Requires-Dist: autopep8
Requires-Dist: isort
Requires-Dist: pyyaml
